README.md
README.rst
setup.py
transcribe/__init__.py
transcribe/__main__.py
transcribe/environ.py
transcribe/image.py
transcribe/path.py
transcribe/speech.py
transcribe/utils.py
transcribe.egg-info/PKG-INFO
transcribe.egg-info/SOURCES.txt
transcribe.egg-info/dependency_links.txt
transcribe.egg-info/entry_points.txt
transcribe.egg-info/requires.txt
transcribe.egg-info/top_level.txt